{
  "SET_INCORRECT_ACTION_TYPE": "action类型设置错误",
  "CANNOT_SET_ACTION": "无法设置action",
  "NO_VALID_DEVICE_SPEC": "非法设备规范",
  "CANNOT_GET_DEVICE_SPEC": "无法获取设备规范",
  "GET_SERVICE_STATE_FAIL_INVALID_CALLBACK": "获取服务状态失败, 非法的回调函数",
  "SERVICE_NOT_FOUND": "未知服务",
  "DEVICE_IN_ACTION": "设备处理调用中",
  "GET_HARDWARE_ADDR_FAIL": "获取设备硬件地址失败",
  "DEVICE_SPEC_UPDATE_FAIL": "设备规范更新失败",
  "EVENT_SUBSCRIBER_TYPE_ERROR": "事件订阅者类型错误",
  "PRESENTATION_NOT_SUPPORTED": "设备不支持表现URL",
  "GET_DEVICE_ROOTURL_FAIL": "获取设备根URL失败",
  "PARSE_DEVICE_ROOTURL_FAIL": "解析设备根URL失败",
  "GET_DEVICE_SCHEMADOC_FAIL": "获取设备schema文档失败",
  "INVALID_DEVICE_SCHEMADOC": "非法设备schema文档",
  "INVALID_JSON_POINTER": "非法JSON指针",
  "POINTER_DEREF_ERROR": "JSON指针解析失败",
  "CANNOT_SET_OAUTH_ACCESS_TOKEN_INVALID_INTERFACE": "无法设置OAuth访问token，无效接口",
  "PROXY_SERVER_CREATE_FAIL": "创建反向代理服务器失败",
  "LOAD_MODULE_FILE_FAIL": "装载模块文件失败",
  "DEVICE_CONNECT_FAIL": "设备连接失败",
  "INVALID_REDIRECT_URL": "非法重定向URL",
  "DEVICE_DISCONNECT_FAIL": "设备断开连接失败",
  "DEVICE_NOT_CONNECTED": "设备未连接",
  "INVALID_ACCESS_TOKEN": "非法访问token",
  "CANNOT_VERIFY_ACCESS_TOKEN": "无法校验访问token",
  "DEVICE_SPEC_VALIDATION_FAIL": "设备规范校验失败",
  "INVALID_MODULE_INSTANCE": "非法设备模块实例",
  "DEVICE_ID_GENERATION_FAIL": "设备ID生成失败",
  "DEVICE_OBJECT_CONFLICT": "设备对象冲突",
  "DEVICE_OFFLINE": "设备已下线",
  "MODULE_VERIFICATION_FAILED": "设备模块校验失败",
  "DEVICE_NOT_FOUND": "未找到设备",
  "MODULE_IN_DISCOVERING": "设备模块发现中",
  "OAUTH_ACCESS_TOKEN_NOT_AVAILABLE": "OAuth访问token不可用",
  "CANNOT_GENERATE_ACCESS_TOKEN": "无法生成访问token",
  "DEVICE_ACTION_CALL_FAIL": "调用设备接口失败",
  "DEVICE_OBJECT_NOT_VALID_CDIF_DEVICE": "设备对象不是合法的CDIF设备",
  "CORRESPONDING_MODULE_NOT_FOUND": "未找到相应设备模块",
  "LOAD_MODULE_FAIL": "模块加载失败",
  "GET_MODULE_INFO_FAIL": "模块信息获取失败",
  "MODULE_NAME_TYPE_ERROR": "模块名称类型错误",
  "READ_MODULE_FAIL": "模块读取失败",
  "UNZIP_MODULE_FAIL": "模块解压失败",
  "UNTAR_MODULE_FAIL": "模块解包失败",
  "MODULE_PACKAGE_INFO_INVALID": "模块信息文件非法",
  "MODULE_PACKAGE_INFO_TYPE_ERROR": "模块信息类型错误",
  "MODULE_PACKAGE_NAME_TYPE_ERROR": "模块名称类型错误",
  "MODULE_VERSION_INFO_INVALID": "模块版本信息不合法",
  "MODULE_INFO_CONTAINS_PUBLISHCONFIG": "模块信息包含publishConfig字段",
  "MODULE_INSTALL_FAIL": "模块安装失败",
  "USERNAME_INVALID": "用户名非法",
  "PASSWORD_INVALID": "密码非法",
  "SCHEMA_COMPILE_ERROR": "schema编译错误",
  "SET_SERVICE_STATE_ERROR": "setServiceState调用错误",
  "SERVICEID_NOT_AVAILABLE": "未找到serviceID",
  "ACTIONNAME_NOT_AVAILABLE": "未找到actionName",
  "ARGUMENTS_INVALID": "调用参数非法",
  "MISSING_INPUT_ARGUMENT": "未找到输入参数",
  "MISSING_OUTPUT_ARGUMENT": "未找到输出参数",
  "DATA_VALIDATION_FAIL": "数据校验错误",
  "ACTION_NOT_FOUND": "未找到action",
  "INPUT_NOT_FOUND": "未找到input对象",
  "ACTION_NOT_IMPLEMENTED": "action未实现",
  "NOT_ENOUGH_USER_BALANCE": "用户余额不足",
  "DEVICE_INVOKE_EXCEPTION": "设备调用异常",
  "DEVICE_INVOKE_FAIL": "设备调用失败",
  "EVENT_SUBSCRIPTION_FAIL": "事件订阅失败",
  "EVENT_UNSUBSCRIPTION_FAIL": "事件退订失败",
  "DEVICE_ACCESS_ERROR": "设备访问失败",
  "DEVICE_NOT_RESPONDING": "设备无响应",
  "SOCKET_SERVER_UNSUBSCRIBE_FAIL": "Socket服务器事件退订失败",
  "NO_VALID_CLIENT_KEY": "WebSocket客户端key非法",
  "WEBSOCKET_SERVER_ERROR": "WebSocket服务器错误",
  "WEBSOCKET_UNSUBSCRIPTION_ERROR": "WebSocket服务器事件退订失败",
  "WEBSOCKET_REMOVE_SUBSCRIBER_ERROR": "WebSocket服务器删除订阅者失败",
  "WEBSOCKET_ERROR": "WebSocket错误",
  "REDIS_CLIENT_ERROR": "redis客户端错误",
  "SYSTEM_ERROR": "系统错误",
  "SYSTEM_ERROR_NETWORK_ERROR": "网络访问错误",
  "SYSTEM_ERROR_DATA_PARSE_ERROR": "数据解析错误",
  "SYSTEM_ERROR_USERDB_NA": "用户数据库不可用",
  "SYSTEM_ERROR_SMSTMPLDB_NA": "模板数据库不可用",
  "SYSTEM_ERROR_USER_UNAUTHORIZED": "用户未经授权",
  "SYSTEM_ERROR_UNKNOWN_USER": "未知用户",
  "API_ERROR": "API调用错误",
  "DATA_ERROR": "API数据错误"
}